{
    "name": "Global Information",
    "numberOfRequests": {
        "total": 4,
        "ok": 4,
        "ko": 0
    },
    "minResponseTime": {
        "total": 186,
        "ok": 186,
        "ko": 0
    },
    "maxResponseTime": {
        "total": 383,
        "ok": 383,
        "ko": 0
    },
    "meanResponseTime": {
        "total": 281,
        "ok": 281,
        "ko": 0
    },
    "standardDeviation": {
        "total": 94,
        "ok": 94,
        "ko": 0
    },
    "percentiles1": {
        "total": 277,
        "ok": 277,
        "ko": 0
    },
    "percentiles2": {
        "total": 370,
        "ok": 370,
        "ko": 0
    },
    "percentiles3": {
        "total": 380,
        "ok": 380,
        "ko": 0
    },
    "percentiles4": {
        "total": 382,
        "ok": 382,
        "ko": 0
    },
    "group1": {
        "name": "t < 800 ms",
        "count": 4,
        "percentage": 100
    },
    "group2": {
        "name": "800 ms < t < 1200 ms",
        "count": 0,
        "percentage": 0
    },
    "group3": {
        "name": "t > 1200 ms",
        "count": 0,
        "percentage": 0
    },
    "group4": {
        "name": "failed",
        "count": 0,
        "percentage": 0
    },
    "meanNumberOfRequestsPerSecond": {
        "total": 0.6666666666666666,
        "ok": 0.6666666666666666,
        "ko": 0
    }
}